kw_template_matcher/__init__.py
kw_template_matcher/opm.py
kw_template_matcher/version.py
keyword_template_matcher-0.1.1.dist-info/METADATA
keyword_template_matcher-0.1.1.dist-info/WHEEL
keyword_template_matcher-0.1.1.dist-info/entry_points.txt
keyword_template_matcher-0.1.1.dist-info/top_level.txt
keyword_template_matcher-0.1.1.dist-info/RECORD
