Metadata-Version: 2.1
Name: keyword-template-matcher
Version: 0.1.1
Summary: A lightweight Python utility for template expansion and matching with slots and fuzzy matching.
Home-page: https://github.com/TigreGotico/kw-template-matcher
Author: JarbasAI
Author-email: jarbasai@mailfence.com
Classifier: Programming Language :: Python :: 3
Classifier: License :: OSI Approved :: MIT License
Classifier: Operating System :: OS Independent
Requires-Python: >=3.9
Requires-Dist: rapidfuzz
Requires-Dist: simplematch
